src/__init__.py
src/core.py
DASST-0.0.1.dist-info/METADATA
DASST-0.0.1.dist-info/WHEEL
DASST-0.0.1.dist-info/top_level.txt
DASST-0.0.1.dist-info/RECORD
